opswork/__init__.py
opswork/cli.py
opswork/command/__init__.py
opswork/command/batch.py
opswork/command/configs.py
opswork/command/hosts.py
opswork/command/random.py
opswork/command/recipes.py
opswork/command/secret.py
opswork/exception/__init__.py
opswork/model/__init__.py
opswork/model/host.py
opswork/model/recipe.py
opswork/model/secret.py
opswork/model/task.py
opswork/module/__init__.py
opswork/module/config.py
opswork/module/database.py
opswork/module/encrypt.py
opswork/module/file_system.py
opswork/module/logger.py
opswork/module/output.py
opswork/module/playbook.py
opswork-0.10.2.dist-info/licenses/LICENSE.txt
opswork-0.10.2.dist-info/METADATA
opswork-0.10.2.dist-info/WHEEL
opswork-0.10.2.dist-info/entry_points.txt
opswork-0.10.2.dist-info/top_level.txt
opswork-0.10.2.dist-info/RECORD
