Metadata-Version: 2.4
Name: opswork
Version: 0.10.2
Summary: OpsWork Swiss Knife.
Home-page: https://github.com/Clivern/OpsWork/
Author: Clivern
Author-email: hello@clivern.com
License: MIT
Project-URL: Documentation, https://github.com/Clivern/OpsWork/
Project-URL: Source, https://github.com/Clivern/OpsWork/
Project-URL: Changelog, https://github.com/Clivern/OpsWork/blob/main/CHANGELOG.rst
Project-URL: Tracker, https://github.com/Clivern/OpsWork/issues
Project-URL: Download, https://pypi.org/project/OpsWork/#files
Platform: any
Classifier: Development Status :: 5 - Production/Stable
Classifier: Programming Language :: Python
Classifier: License :: OSI Approved :: MIT License
License-File: LICENSE.txt
Requires-Dist: click<=8.3.0
Requires-Dist: ansible-runner<=2.4.2
Requires-Dist: prettytable<=3.17.0
Requires-Dist: PyYAML<=6.0.3
Requires-Dist: cryptography<=46.0.3
Requires-Dist: GitPython<=3.1.45
Requires-Dist: requests<=2.32.5
Requires-Dist: importlib-metadata<=8.7.0; python_version < "3.8"
Dynamic: license-file
